skelly/__init__.py
skelly/main.py
simple_video_to_skeletal_animation-0.1.dist-info/LICENSE.txt
simple_video_to_skeletal_animation-0.1.dist-info/METADATA
simple_video_to_skeletal_animation-0.1.dist-info/WHEEL
simple_video_to_skeletal_animation-0.1.dist-info/top_level.txt
simple_video_to_skeletal_animation-0.1.dist-info/RECORD
