Metadata-Version: 2.1
Name: simple-video-to-skeletal-animation
Version: 0.1
Summary: This package will allow you to provide a video and get an animated skeleton
Home-page: https://github.com/professorcode1/simple-video-to-skeletal-animation
Author: Raghav Kumar
Author-email: raghkum2000@gmail.com
Classifier: License :: OSI Approved :: MIT License
License-File: LICENSE.txt
